cyanDiff/__init__.py
cyanDiff/ad_helpers.py
cyanDiff/ad_overloads.py
cyanDiff/ad_types.py
cyanDiff/critical_points.py
cyanDiff/newton_raphson.py
cyanDiff/reverse_mode.py
cyandiff-0.3.dist-info/METADATA
cyandiff-0.3.dist-info/WHEEL
cyandiff-0.3.dist-info/licenses/LICENSE
cyandiff-0.3.dist-info/RECORD
